[
  {
    "filename": "2124813.mp3",
    "used_at": "2026-05-15T07:01:00.675218",
    "pillar": "story_proof"
  },
  {
    "filename": "2280561.mp3",
    "used_at": "2026-05-15T15:23:51.647326",
    "pillar": "reframe"
  },
  {
    "filename": "1876634.mp3",
    "used_at": "2026-05-16T06:39:03.153034",
    "pillar": "hard_truth"
  },
  {
    "filename": "1411145.mp3",
    "used_at": "2026-05-16T14:37:32.599622",
    "pillar": "tactical"
  },
  {
    "filename": "2163964.mp3",
    "used_at": "2026-05-17T06:51:13.337137",
    "pillar": "reframe"
  },
  {
    "filename": "2038811.mp3",
    "used_at": "2026-05-17T14:19:23.588415",
    "pillar": "hard_truth"
  },
  {
    "filename": "1533554.mp3",
    "used_at": "2026-05-18T07:25:46.322393",
    "pillar": "tactical"
  },
  {
    "filename": "1981752.mp3",
    "used_at": "2026-05-18T16:16:13.328788",
    "pillar": "story_proof"
  },
  {
    "filename": "2007484.mp3",
    "used_at": "2026-05-19T07:22:48.442866",
    "pillar": "reframe"
  },
  {
    "filename": "1933339.mp3",
    "used_at": "2026-05-19T16:19:26.477994",
    "pillar": "story_proof"
  },
  {
    "filename": "1401629.mp3",
    "used_at": "2026-05-20T07:28:59.478663",
    "pillar": "tactical"
  },
  {
    "filename": "168834.mp3",
    "used_at": "2026-05-20T16:33:00.452853",
    "pillar": "hard_truth"
  },
  {
    "filename": "2280561.mp3",
    "used_at": "2026-05-21T07:35:08.751527",
    "pillar": "reframe"
  },
  {
    "filename": "1826189.mp3",
    "used_at": "2026-05-21T16:19:48.040936",
    "pillar": "story_proof"
  },
  {
    "filename": "1445708.mp3",
    "used_at": "2026-05-22T07:28:05.663764",
    "pillar": "tactical"
  }
]