{
  "best_topic": "switch\" your mind",
  "trending_topics": [
    "switch\" your mind",
    "how to build discipline",
    "how to develop self discipline",
    "wake up early",
    "cristiano ronaldo talks about discipline",
    "if you don't have discipline you are a nobody",
    "born for discipline",
    "every delay is a vote against yourself",
    "your phone is stealing your future",
    "nobody is coming to save you"
  ],
  "hot_keywords": [
    "every",
    "day",
    "follow",
    "work",
    "discipline",
    "hard",
    "become",
    "think",
    "isn",
    "don"
  ],
  "google_trends": [
    "tsmc",
    "hyunjung lee",
    "bryson dechambeau",
    "hal williams",
    "carl isom mcdaniel bison encounter"
  ],
  "source": "youtube",
  "timestamp": "2026-07-16T06:23:10.485618"
}