{
  "best_topic": "portable shooting machine x founder, ceo",
  "trending_topics": [
    "portable shooting machine x founder, ceo",
    "you are not unlucky you are undisciplined",
    "your future self is watching you right now",
    "you already know what you need to do",
    "you are not busy you are avoiding",
    "fear is just comfort in disguise",
    "wake up before your competition does",
    "you keep choosing comfort over growth",
    "the clock does not care about your excuses",
    "every delay is a vote against yourself"
  ],
  "hot_keywords": [
    "day",
    "follow",
    "life",
    "every",
    "bad",
    "think",
    "doesn",
    "people",
    "body",
    "don"
  ],
  "google_trends": [
    "jason statham",
    "axios",
    "leslie jones",
    "ai bubble",
    "tom pelissero"
  ],
  "source": "youtube",
  "timestamp": "2026-07-21T14:59:32.145246"
}